.travis.yml
LICENSE
MANIFEST.in
README.rst
dev-requirements.txt
setup.cfg
setup.py
tox.ini
Mopidy_Spotify_Tunigo.egg-info/PKG-INFO
Mopidy_Spotify_Tunigo.egg-info/SOURCES.txt
Mopidy_Spotify_Tunigo.egg-info/dependency_links.txt
Mopidy_Spotify_Tunigo.egg-info/entry_points.txt
Mopidy_Spotify_Tunigo.egg-info/not-zip-safe
Mopidy_Spotify_Tunigo.egg-info/requires.txt
Mopidy_Spotify_Tunigo.egg-info/top_level.txt
mopidy_spotify_tunigo/__init__.py
mopidy_spotify_tunigo/backend.py
mopidy_spotify_tunigo/ext.conf
mopidy_spotify_tunigo/library.py
mopidy_spotify_tunigo/translator.py
tests/__init__.py
tests/conftest.py
tests/test_backend.py
tests/test_extension.py
tests/test_library.py
tests/test_translator.py