Metadata-Version: 1.1
Name: Mopidy-Spotify-Tunigo
Version: 1.0.0
Summary: Mopidy extension for providing the browse feature of Spotify
Home-page: https://github.com/trygveaa/mopidy-spotify-tunigo
Author: Trygve Aaberge
Author-email: trygveaa@gmail.com
License: Apache License, Version 2.0
Platform: UNKNOWN
Classifier: Environment :: No Input/Output (Daemon)
Classifier: Intended Audience :: End Users/Desktop
Classifier: License :: OSI Approved :: Apache Software License
Classifier: Operating System :: OS Independent
Classifier: Programming Language :: Python :: 2
Classifier: Programming Language :: Python :: 2.7
Classifier: Programming Language :: Python :: Implementation :: CPython
Classifier: Programming Language :: Python :: Implementation :: PyPy
Classifier: Topic :: Multimedia :: Sound/Audio :: Players
